bitcoinlib_dev/__init__.py
bitcoinlib_dev/cli.py
bitcoinlib_dev/dbupdate.py
bitcoinlib_dev/init.py
bitcoinlib_dev/installer.py
bitcoinlib_dev/utils.py
bitcoinlib_dev/wallet.py
bitcoinlib_dev-0.4.21.dist-info/LICENSE
bitcoinlib_dev-0.4.21.dist-info/METADATA
bitcoinlib_dev-0.4.21.dist-info/WHEEL
bitcoinlib_dev-0.4.21.dist-info/entry_points.txt
bitcoinlib_dev-0.4.21.dist-info/RECORD
